dora_sim_genesis_franka_grasp_cube-0.0.3.dist-info/licenses/LICENSE
src/config_loader.py
src/keyboard_controller.py
src/main.py
src/main_bc.py
src/print_joint.py
dora_sim_genesis_franka_grasp_cube-0.0.3.dist-info/METADATA
dora_sim_genesis_franka_grasp_cube-0.0.3.dist-info/WHEEL
dora_sim_genesis_franka_grasp_cube-0.0.3.dist-info/entry_points.txt
dora_sim_genesis_franka_grasp_cube-0.0.3.dist-info/top_level.txt
dora_sim_genesis_franka_grasp_cube-0.0.3.dist-info/RECORD
