Metadata-Version: 2.4
Name: dora-sim-genesis-franka-grasp-cube
Version: 0.0.3
Author-email: Xiang Yang <ryu-yang@qq.com>
Requires-Python: <3.14,>=3.10
License-File: LICENSE
Requires-Dist: dora-rs-cli<0.4.0,>=0.3.11
Requires-Dist: genesis-world>=0.3.7
Requires-Dist: torch
Requires-Dist: pynput
Requires-Dist: dora-rerun
Provides-Extra: view
Requires-Dist: dora-rs-cli; extra == "view"
Requires-Dist: dora-rerun; extra == "view"
Dynamic: license-file
